aider/__init__.py
aider/args.py
aider/commands.py
aider/diffs.py
aider/dump.py
aider/gui.py
aider/history.py
aider/io.py
aider/linter.py
aider/litellm.py
aider/main.py
aider/main_wrapper.py
aider/mdstream.py
aider/models.py
aider/prompts.py
aider/repo.py
aider/repomap.py
aider/scrape.py
aider/sendchat.py
aider/utils.py
aider/versioncheck.py
aider/voice.py
aider/coders/__init__.py
aider/coders/base_coder.py
aider/coders/base_prompts.py
aider/coders/editblock_coder.py
aider/coders/editblock_fenced_coder.py
aider/coders/editblock_fenced_prompts.py
aider/coders/editblock_func_coder.py
aider/coders/editblock_func_prompts.py
aider/coders/editblock_prompts.py
aider/coders/search_replace.py
aider/coders/single_wholefile_func_coder.py
aider/coders/single_wholefile_func_prompts.py
aider/coders/udiff_coder.py
aider/coders/udiff_prompts.py
aider/coders/wholefile_coder.py
aider/coders/wholefile_func_coder.py
aider/coders/wholefile_func_prompts.py
aider/coders/wholefile_prompts.py
benchmark/__init__.py
benchmark/benchmark.py
benchmark/over_time.py
benchmark/plots.py
benchmark/prompts.py
benchmark/refactor_tools.py
benchmark/rungrid.py
benchmark/swe_bench.py
benchmark/test_benchmark.py
cli/__init__.py
modules/__init__.py
tests/__init__.py
tests/test_coder.py
tests/test_commands.py
tests/test_editblock.py
tests/test_io.py
tests/test_main.py
tests/test_models.py
tests/test_repo.py
tests/test_repomap.py
tests/test_sendchat.py
tests/test_udiff.py
tests/test_wholefile.py
Agentic_DevOps-0.0.9.dist-info/LICENSE
Agentic_DevOps-0.0.9.dist-info/METADATA
Agentic_DevOps-0.0.9.dist-info/WHEEL
Agentic_DevOps-0.0.9.dist-info/entry_points.txt
Agentic_DevOps-0.0.9.dist-info/top_level.txt
Agentic_DevOps-0.0.9.dist-info/RECORD
