Metadata-Version: 2.1
Name: Agentic-DevOps
Version: 0.0.9
Summary: Agentic DevOps Tool for automating and managing various DevOps tasks and configurations.
Home-page: https://github.com/ruvnet/agentic-devops
Author: rUv
Author-email: null@ruv.net
Classifier: Development Status :: 3 - Alpha
Classifier: Environment :: Console
Classifier: Intended Audience :: Developers
Classifier: License :: OSI Approved :: Apache Software License
Classifier: Programming Language :: Python :: 3
Classifier: Programming Language :: Python :: 3.10
Classifier: Programming Language :: Python :: 3.11
Classifier: Programming Language :: Python :: 3.12
Classifier: Programming Language :: Python :: 3.9
Classifier: Programming Language :: Python
Classifier: Topic :: Software Development
License-File: LICENSE
Requires-Dist: aiohttp ==3.9.5
Requires-Dist: aiosignal ==1.3.1
Requires-Dist: altair ==5.3.0
Requires-Dist: annotated-types ==0.6.0
Requires-Dist: anyio ==4.3.0
Requires-Dist: attrs ==23.2.0
Requires-Dist: backoff ==2.2.1
Requires-Dist: beautifulsoup4 ==4.12.3
Requires-Dist: blinker ==1.8.2
Requires-Dist: cachetools ==5.3.3
Requires-Dist: certifi ==2024.2.2
Requires-Dist: cffi ==1.16.0
Requires-Dist: charset-normalizer ==3.3.2
Requires-Dist: click ==8.1.7
Requires-Dist: configargparse ==1.7
Requires-Dist: diff-match-patch ==20230430
Requires-Dist: diskcache ==5.6.3
Requires-Dist: distro ==1.9.0
Requires-Dist: filelock ==3.14.0
Requires-Dist: flake8 ==7.0.0
Requires-Dist: frozenlist ==1.4.1
Requires-Dist: fsspec ==2024.5.0
Requires-Dist: gitdb ==4.0.11
Requires-Dist: gitpython ==3.1.43
Requires-Dist: google-ai-generativelanguage ==0.6.4
Requires-Dist: google-api-core[grpc] ==2.19.0
Requires-Dist: google-api-python-client ==2.129.0
Requires-Dist: google-auth ==2.29.0
Requires-Dist: google-auth-httplib2 ==0.2.0
Requires-Dist: google-generativeai ==0.5.4
Requires-Dist: googleapis-common-protos ==1.63.0
Requires-Dist: greenlet ==3.0.3
Requires-Dist: grep-ast ==0.3.2
Requires-Dist: grpcio ==1.63.0
Requires-Dist: grpcio-status ==1.62.2
Requires-Dist: h11 ==0.14.0
Requires-Dist: httpcore ==1.0.5
Requires-Dist: httplib2 ==0.22.0
Requires-Dist: httpx ==0.27.0
Requires-Dist: huggingface-hub ==0.23.0
Requires-Dist: idna ==3.7
Requires-Dist: importlib-metadata ==7.1.0
Requires-Dist: jinja2 ==3.1.4
Requires-Dist: jsonschema ==4.22.0
Requires-Dist: jsonschema-specifications ==2023.12.1
Requires-Dist: litellm ==1.37.16
Requires-Dist: markdown-it-py ==3.0.0
Requires-Dist: markupsafe ==2.1.5
Requires-Dist: mccabe ==0.7.0
Requires-Dist: mdurl ==0.1.2
Requires-Dist: multidict ==6.0.5
Requires-Dist: networkx ==3.2.1
Requires-Dist: numpy ==1.26.4
Requires-Dist: openai ==1.30.1
Requires-Dist: packaging ==24.0
Requires-Dist: pandas ==2.2.2
Requires-Dist: pathspec ==0.12.1
Requires-Dist: pillow ==10.3.0
Requires-Dist: playwright ==1.44.0
Requires-Dist: prompt-toolkit ==3.0.43
Requires-Dist: proto-plus ==1.23.0
Requires-Dist: protobuf ==4.25.3
Requires-Dist: pyarrow ==16.1.0
Requires-Dist: pyasn1 ==0.6.0
Requires-Dist: pyasn1-modules ==0.4.0
Requires-Dist: pycodestyle ==2.11.1
Requires-Dist: pycparser ==2.22
Requires-Dist: pydantic ==2.7.1
Requires-Dist: pydantic-core ==2.18.2
Requires-Dist: pydeck ==0.9.1
Requires-Dist: pyee ==11.1.0
Requires-Dist: pyflakes ==3.2.0
Requires-Dist: pygments ==2.18.0
Requires-Dist: pypandoc ==1.13
Requires-Dist: pyparsing ==3.1.2
Requires-Dist: python-dateutil ==2.9.0.post0
Requires-Dist: python-dotenv ==1.0.1
Requires-Dist: pytz ==2024.1
Requires-Dist: pyyaml ==6.0.1
Requires-Dist: referencing ==0.35.1
Requires-Dist: regex ==2024.5.15
Requires-Dist: requests ==2.31.0
Requires-Dist: rich ==13.7.1
Requires-Dist: rpds-py ==0.18.1
Requires-Dist: rsa ==4.9
Requires-Dist: scipy ==1.13.0
Requires-Dist: six ==1.16.0
Requires-Dist: smmap ==5.0.1
Requires-Dist: sniffio ==1.3.1
Requires-Dist: sounddevice ==0.4.6
Requires-Dist: soundfile ==0.12.1
Requires-Dist: soupsieve ==2.5
Requires-Dist: streamlit ==1.34.0
Requires-Dist: tenacity ==8.3.0
Requires-Dist: tiktoken ==0.7.0
Requires-Dist: tokenizers ==0.19.1
Requires-Dist: toml ==0.10.2
Requires-Dist: toolz ==0.12.1
Requires-Dist: tornado ==6.4
Requires-Dist: tqdm ==4.66.4
Requires-Dist: tree-sitter ==0.21.3
Requires-Dist: tree-sitter-languages ==1.10.2
Requires-Dist: typing-extensions ==4.11.0
Requires-Dist: tzdata ==2024.1
Requires-Dist: uritemplate ==4.1.1
Requires-Dist: urllib3 ==2.2.1
Requires-Dist: wcwidth ==0.2.13
Requires-Dist: yarl ==1.9.4
Requires-Dist: zipp ==3.18.2
